ryseble/__init__.py
ryseble/bluetoothctl.py
ryseble/constants.py
ryseble/device.py
ryseble/packets.py
ryseble-1.9.0.dist-info/licenses/LICENSE
ryseble-1.9.0.dist-info/METADATA
ryseble-1.9.0.dist-info/WHEEL
ryseble-1.9.0.dist-info/top_level.txt
ryseble-1.9.0.dist-info/RECORD
