Metadata-Version: 2.4
Name: ryseble
Version: 1.9.0
Summary: Python library for RYSE BLE Smart Shade devices (used by Home Assistant integration).
Author-email: MOHAMED Kallel <mohamed.kallel@yahoo.fr>
License: MIT
Project-URL: Homepage, https://github.com/mohamedkallel82/ryseble
Project-URL: Bug Tracker, https://github.com/mohamedkallel82/ryseble/issues
Classifier: Programming Language :: Python :: 3
Classifier: License :: OSI Approved :: MIT License
Classifier: Operating System :: OS Independent
Requires-Python: >=3.9
License-File: LICENSE
Requires-Dist: bleak>=0.22.0
Dynamic: license-file
